beunique/__init__.py
beunique/first.py
todo/__init__.py
todo/first.py
beunique-0.1.3.dist-info/LICENSE
beunique-0.1.3.dist-info/METADATA
beunique-0.1.3.dist-info/WHEEL
beunique-0.1.3.dist-info/top_level.txt
beunique-0.1.3.dist-info/RECORD
