Metadata-Version: 2.1
Name: beunique
Version: 0.1.3
Summary: A todo app to understand the building packages.
Home-page: https://github.com/Dara-Ekanth/todo_custom_package
Author: Dara Ekanth
Author-email: daraekanth3@gmail.com
License: UNKNOWN
Project-URL: Bug Tracker, https://github.com/Dara-Ekanth/todo_custom_package/issues
Keywords: python,data collection,data science,ML,todo,custom,custom package,beunique
Platform: UNKNOWN
Classifier: Development Status :: 1 - Planning
Classifier: Intended Audience :: Developers
Classifier: Programming Language :: Python :: 3
Classifier: Programming Language :: Python :: 3.7
Classifier: Programming Language :: Python :: 3.8
Classifier: Operating System :: Unix
Classifier: Operating System :: MacOS :: MacOS X
Classifier: Operating System :: Microsoft :: Windows
Classifier: License :: OSI Approved :: MIT License
Requires-Dist: pandas
